pyinno_gen/__init__.py
pyinno_gen/pyinno_gen.py
pyinno_gen/test/template.iss
pyinno_gen/test/test_tempalte.py
pyinno_gen-0.0.12.dist-info/licenses/LICENSE
pyinno_gen-0.0.12.dist-info/METADATA
pyinno_gen-0.0.12.dist-info/WHEEL
pyinno_gen-0.0.12.dist-info/top_level.txt
pyinno_gen-0.0.12.dist-info/RECORD
