Metadata-Version: 2.4
Name: pyinno_gen
Version: 0.0.12
Summary: module for programmatically generating iss file from jinja template for innosetup installer generater
Author-email: keralaboy <keralaboypypi@keralaboy.anonaddy.com>
License-Expression: MIT
Project-URL: Homepage, https://github.com/its-me-abi/pyinno_gen
Keywords: compiler,inno setup,exe,installer,generate,.iss
Classifier: Development Status :: 4 - Beta
Classifier: Programming Language :: Python
Requires-Python: >=3.6
License-File: LICENSE
Requires-Dist: Jinja2
Dynamic: license-file
